Metadata-Version: 1.0
Name: smake-buildtools
Version: 0.1.2
Summary: Simple Make replacement for developers who love Python
Home-page: https://github.com/qetyzm/smake
Author: Qetyzm
Author-email: qetyzm@gmail.com
License: MIT License
